xnattagger/__init__.py
xnattagger/__version__.py
xnattagger/config/__init__.py
xnattagger/config/tagger.yaml
xnattagger_kkurk-1.0.0.data/scripts/xnat_tagger.py
xnattagger_kkurk-1.0.0.dist-info/licenses/LICENSE
xnattagger_kkurk-1.0.0.dist-info/METADATA
xnattagger_kkurk-1.0.0.dist-info/WHEEL
xnattagger_kkurk-1.0.0.dist-info/top_level.txt
xnattagger_kkurk-1.0.0.dist-info/RECORD
